lab4/lab4_1/sim/lab4_1.v
module	lab4_1(clk, reset, row, sel, column_green, column_red);
input 	clk,reset;
input	[1:0]sel;
output	[7:0]row, column_green, column_red;
wire 	clk_row, clk_idx;
wire	[6:0]idx, idx_cnt;
wire	[7:0]column_out;

assign 	column_green= (sel== 2'b01 || sel== 2'b11)? column_out: 8'b0;
assign 	column_red	= (sel== 2'b10 || sel== 2'b11)? column_out: 8'b0;

//freq_div#(22) M1 (clk,reset,clk_idx);
freq_div#(6) M1 (clk,reset,clk_idx);
//freq_div#(12) M2 (clk,reset,clk_row);
freq_div#(1) M2 (clk,reset,clk_row);
idx_gen M3 (clk_idx,reset,idx); 
row_gen M4 (clk_row,reset, idx, row, idx_cnt);
rom_char M5 (idx_cnt, column_out);
endmodule
//---------------------------------------------------------------------
module 	rom_char(addr, data);
input	[6:0]addr;
output	[7:0]data;
reg		[7:0]data;

always@(addr) 
begin
	case(addr)
	7'd0: 	data=8'b00000000;		
	7'd1: 	data=8'b00000000;	
	7'd2: 	data=8'b00000000; 	
	7'd3: 	data=8'b00000000;
	7'd4: 	data=8'b00000000;		
	7'd5: 	data=8'b00000000;	
	7'd6: 	data=8'b00000000;		
	7'd7: 	data=8'b00000000;
	//-----------------------
	7'd8: 	data=8'b00111100;		
	7'd9: 	data=8'b01000010;	
	7'd10: 	data=8'b01000110; 	
	7'd11: 	data=8'b01001010;
	7'd12: 	data=8'b01010010;	
	7'd13: 	data=8'b01100010;
	7'd14: 	data=8'b00111100;	
	7'd15: 	data=8'b00000000;
	//-----------------------

	7'd16: 	data=8'b00001000;	
	7'd17: 	data=8'b00011000;
	7'd18: 	data=8'b00001000;	
	7'd19: 	data=8'b00001000;
	7'd20: 	data=8'b00001000;	
	7'd21: 	data=8'b00001000;
	7'd22: 	data=8'b00011100;	
	7'd23: 	data=8'b00000000;
	//
	7'd24: 	data=8'b00111100;	
	7'd25: 	data=8'b01000010;
	7'd26: 	data=8'b01000010;	
	7'd27: 	data=8'b00000100;
	7'd28: 	data=8'b00001000;	
	7'd29: 	data=8'b00010000;
	7'd30: 	data=8'b01111110;	
	7'd31: 	data=8'b00000000;
	//
	7'd32: 	data=8'b00111100; 	
	7'd33: 	data=8'b01000010;
	7'd34: 	data=8'b00000010;	
	7'd35: 	data=8'b00111100;
	7'd36: 	data=8'b00000010;	
	7'd37: 	data=8'b01000010;
	7'd38: 	data=8'b00111100;	
	7'd39: 	data=8'b00000000;
	//
	7'd40: 	data=8'b00011100; 	
	7'd41: 	data=8'b00100100;
	7'd42: 	data=8'b01000100;	
	7'd43: 	data=8'b01000100;
	7'd44: 	data=8'b01000100;	
	7'd45: 	data=8'b01111110;
	7'd46: 	data=8'b00000100;	
	7'd47: 	data=8'b00000000;
	//
	7'd48: 	data=8'b01111110;	
	7'd49: 	data=8'b01000000;
	7'd50: 	data=8'b01000000;	
	7'd51: 	data=8'b01111100;
	7'd52: 	data=8'b00000010;	
	7'd53: 	data=8'b01000010;
	7'd54: 	data=8'b00111100;	
	7'd55: 	data=8'b00000000;
	//
	7'd56:	data=8'b00111100;
	7'd57:	data=8'b01000000;
	7'd58:	data=8'b01000000;
	7'd59:	data=8'b01111100;
	7'd60:	data=8'b01000010;
	7'd61:	data=8'b01000010;
	7'd62:	data=8'b00111100;
	7'd63:	data=8'b00000000;
	//-----------------------
	7'd64:	data=8'b00111100;
	7'd65:	data=8'b01000010;
	7'd66:	data=8'b01000010;
	7'd67:	data=8'b00000010;
	7'd68:	data=8'b00000100;
	7'd69:	data=8'b00000100;
	7'd70:	data=8'b00000100;
	7'd71:	data=8'b00000000;
	//-----------------------
	7'd72:	data=8'b00111100;
	7'd73:	data=8'b01000010;
	7'd74:	data=8'b01000010;
	7'd75:	data=8'b00111100;
	7'd76:	data=8'b01000010;
	7'd77:	data=8'b01000010;
	7'd78:	data=8'b00111100;
	7'd79:	data=8'b00000000;
	//-----------------------
	7'd80:	data=8'b00111100;
	7'd81:	data=8'b01000010;
	7'd82:	data=8'b01000010;
	7'd83:	data=8'b00111100;
	7'd84:	data=8'b00000010;
	7'd85:	data=8'b00000010;
	7'd86:	data=8'b00000010;
	7'd87:	data=8'b00000000;
	endcase
end
endmodule
//---------------------------------------------------
module 	idx_gen(clk, reset, idx);
input 	clk,reset;
output	[6:0]idx;
reg		[6:0]idx;

always@(posedge clk or posedge reset) 
begin
	if(reset)
		idx= 7'd0;
	else if(idx==7'd80)
			idx= 7'd0;
		else
			idx=idx+7'd08;
end
endmodule
//---------------------------------------------------
module 	row_gen(clk, reset, idx, row, idx_cnt);
input 	clk, reset;
input	[6:0]idx;
output	[7:0]row;
output	[6:0]idx_cnt;
reg		[7:0]row;
reg		[6:0]idx_cnt;
reg		[2:0]cnt;

always@(posedge clk or posedge reset) 
begin
	if(reset) begin
		row		=8'b1000_0000;
		cnt		=3'd0;
		idx_cnt	=7'd0;
		end
	else begin
		row		={row[0],row[7:1]} ;    	//(輪流將每一列LED致能)
		cnt		=cnt+3'd1;        	//(從0數到7) 
		idx_cnt	=idx+cnt;  	//(將初始位置加0到7)
		end
end
endmodule
//---------------------------------------------------
module 		freq_div(clk_in,reset,clk_out);

parameter	exp = 20;   
input		clk_in, reset;
output		clk_out;
reg			[exp-1:0] divider;
integer 	i;

assign 	clk_out= divider[exp-1];

always@ (posedge clk_in or posedge reset)
begin
	if(reset)
		for(i=0; i < exp; i=i+1)
		divider[i] = 1'b0;
	else
		divider = divider+ 1'b1;
end
endmodule
//--------------------------------------------------

lab4/lab4_1/sim/lab4_1_tb.v
`timescale 1 ns/1 ns

module 	lab4_1_tb;

reg 	clk,reset;
reg		[1:0]sel;
wire	[7:0]row, column_green, column_red;
wire 	clk_shift, clk_scan;
wire	[7:0]idx, idx_cnt;
wire	[7:0]column_out;

lab4_1 lab4_1(
						.clk(clk),
						.reset(reset),
						.row(row),
						.sel(sel),
						.column_green(column_green),
						.column_red(column_red)			);

// set up clk with 50 ns period 20 MHz
parameter	clkper = 5;
parameter	exp = 1;

initial
begin
	clk = 1;	// Time = 0
end

always 
begin
	#(clkper / 2)  clk = ~clk;
end

initial
begin
 reset	=1'b1;
 #20;		
 reset  =1'b0;
 sel	= 2'b01;
 #1000;	
 $finish;		
end

initial begin
	$dumpfile("lab4_1.vcd");
	$dumpvars;
end

endmodule

lab4/lab4_1/sim/lab4_1.vcd
$date
	Thu Jan 14 21:29:10 2021
$end
$version
	Icarus Verilog
$end
$timescale
	1ns
$end
$scope module lab4_1_tb $end
$var wire 8 ! row [7:0] $end
$var wire 8 " column_red [7:0] $end
$var wire 8 # column_green [7:0] $end
$var reg 1 $ clk $end
$var reg 1 % reset $end
$var reg 2 & sel [1:0] $end
$scope module lab4_1 $end
$var wire 1 $ clk $end
$var wire 1 % reset $end
$var wire 2 ' sel [1:0] $end
$var wire 8 ( row [7:0] $end
$var wire 7 ) idx_cnt [6:0] $end
$var wire 7 * idx [6:0] $end
$var wire 8 + column_red [7:0] $end
$var wire 8 , column_out [7:0] $end
$var wire 8 - column_green [7:0] $end
$var wire 1 . clk_row $end
$var wire 1 / clk_idx $end
$scope module M1 $end
$var wire 1 $ clk_in $end
$var wire 1 % reset $end
$var wire 1 / clk_out $end
$var reg 6 0 divider [5:0] $end
$var integer 32 1 i [31:0] $end
$upscope $end
$scope module M2 $end
$var wire 1 $ clk_in $end
$var wire 1 . clk_out $end
$var wire 1 % reset $end
$var reg 1 2 divider $end
$var integer 32 3 i [31:0] $end
$upscope $end
$scope module M3 $end
$var wire 1 / clk $end
$var wire 1 % reset $end
$var reg 7 4 idx [6:0] $end
$upscope $end
$scope module M4 $end
$var wire 1 . clk $end
$var wire 7 5 idx [6:0] $end
$var wire 1 % reset $end
$var reg 3 6 cnt [2:0] $end
$var reg 7 7 idx_cnt [6:0] $end
$var reg 8 8 row [7:0] $end
$upscope $end
$scope module M5 $end
$var wire 7 9 addr [6:0] $end
$var reg 8 : data [7:0] $end
$upscope $end
$upscope $end
$upscope $end
$enddefinitions $end
#0
$dumpvars
b0 :
b0 9
b10000000 8
b0 7
b0 6
b0 5
b0 4
b1 3
02
b110 1
b0 0
0/
0.
b0 -
b0 ,
b0 +
b0 *
b0 )
b10000000 (
bx '
bx &
1%
1$
b0 #
b0 "
b10000000 !
$end
#2
0$
#4
b1 3
b110 1
1$
#6
0$
#8
b110 1
b1 3
1$
#10
0$
#12
b1 3
b110 1
1$
#14
0$
#16
b110 1
b1 3
1$
#18
0$
#20
b1 )
b1 7
b1 9
b1 6
b1000000 !
b1000000 (
b1000000 8
1.
12
b1 0
1$
b1 &
b1 '
0%
#22
0$
#24
b10 0
0.
02
1$
#26
0$
#28
b10 )
b10 7
b10 9
b10 6
b100000 !
b100000 (
b100000 8
1.
12
b11 0
1$
#30
0$
#32
b100 0
0.
02
1$
#34
0$
#36
b11 )
b11 7
b11 9
b11 6
b10000 !
b10000 (
b10000 8
1.
12
b101 0
1$
#38
0$
#40
b110 0
0.
02
1$
#42
0$
#44
b100 )
b100 7
b100 9
b100 6
b1000 !
b1000 (
b1000 8
1.
12
b111 0
1$
#46
0$
#48
b1000 0
0.
02
1$
#50
0$
#52
b101 )
b101 7
b101 9
b101 6
b100 !
b100 (
b100 8
1.
12
b1001 0
1$
#54
0$
#56
b1010 0
0.
02
1$
#58
0$
#60
b110 )
b110 7
b110 9
b110 6
b10 !
b10 (
b10 8
1.
12
b1011 0
1$
#62
0$
#64
b1100 0
0.
02
1$
#66
0$
#68
b111 )
b111 7
b111 9
b111 6
b1 !
b1 (
b1 8
1.
12
b1101 0
1$
#70
0$
#72
b1110 0
0.
02
1$
#74
0$
#76
b0 )
b0 7
b0 9
b0 6
b10000000 !
b10000000 (
b10000000 8
1.
12
b1111 0
1$
#78
0$
#80
b10000 0
0.
02
1$
#82
0$
#84
b1 )
b1 7
b1 9
b1 6
b1000000 !
b1000000 (
b1000000 8
1.
12
b10001 0
1$
#86
0$
#88
b10010 0
0.
02
1$
#90
0$
#92
b10 )
b10 7
b10 9
b10 6
b100000 !
b100000 (
b100000 8
1.
12
b10011 0
1$
#94
0$
#96
b10100 0
0.
02
1$
#98
0$
#100
b11 )
b11 7
b11 9
b11 6
b10000 !
b10000 (
b10000 8
1.
12
b10101 0
1$
#102
0$
#104
b10110 0
0.
02
1$
#106
0$
#108
b100 )
b100 7
b100 9
b100 6
b1000 !
b1000 (
b1000 8
1.
12
b10111 0
1$
#110
0$
#112
b11000 0
0.
02
1$
#114
0$
#116
b101 )
b101 7
b101 9
b101 6
b100 !
b100 (
b100 8
1.
12
b11001 0
1$
#118
0$
#120
b11010 0
0.
02
1$
#122
0$
#124
b110 )
b110 7
b110 9
b110 6
b10 !
b10 (
b10 8
1.
12
b11011 0
1$
#126
0$
#128
b11100 0
0.
02
1$
#130
0$
#132
b111 )
b111 7
b111 9
b111 6
b1 !
b1 (
b1 8
1.
12
b11101 0
1$
#134
0$
#136
b11110 0
0.
02
1$
#138
0$
#140
b0 )
b0 7
b0 9
b0 6
b10000000 !
b10000000 (
b10000000 8
1.
12
b11111 0
1$
#142
0$
#144
b1000 *
b1000 4
b1000 5
1/
b100000 0
0.
02
1$
#146
0$
#148
b1000010 #
b1000010 -
b1000010 ,
b1000010 :
b1001 )
b1001 7
b1001 9
b1 6
b1000000 !
b1000000 (
b1000000 8
1.
12
b100001 0
1$
#150
0$
#152
b100010 0
0.
02
1$
#154
0$
#156
b1000110 #
b1000110 -
b1000110 ,
b1000110 :
b1010 )
b1010 7
b1010 9
b10 6
b100000 !
b100000 (
b100000 8
1.
12
b100011 0
1$
#158
0$
#160
b100100 0
0.
02
1$
#162
0$
#164
b1001010 #
b1001010 -
b1001010 ,
b1001010 :
b1011 )
b1011 7
b1011 9
b11 6
b10000 !
b10000 (
b10000 8
1.
12
b100101 0
1$
#166
0$
#168
b100110 0
0.
02
1$
#170
0$
#172
b1010010 #
b1010010 -
b1010010 ,
b1010010 :
b1100 )
b1100 7
b1100 9
b100 6
b1000 !
b1000 (
b1000 8
1.
12
b100111 0
1$
#174
0$
#176
b101000 0
0.
02
1$
#178
0$
#180
b1100010 #
b1100010 -
b1100010 ,
b1100010 :
b1101 )
b1101 7
b1101 9
b101 6
b100 !
b100 (
b100 8
1.
12
b101001 0
1$
#182
0$
#184
b101010 0
0.
02
1$
#186
0$
#188
b111100 #
b111100 -
b111100 ,
b111100 :
b1110 )
b1110 7
b1110 9
b110 6
b10 !
b10 (
b10 8
1.
12
b101011 0
1$
#190
0$
#192
b101100 0
0.
02
1$
#194
0$
#196
b0 #
b0 -
b0 ,
b0 :
b1111 )
b1111 7
b1111 9
b111 6
b1 !
b1 (
b1 8
1.
12
b101101 0
1$
#198
0$
#200
b101110 0
0.
02
1$
#202
0$
#204
b111100 #
b111100 -
b111100 ,
b111100 :
b1000 )
b1000 7
b1000 9
b0 6
b10000000 !
b10000000 (
b10000000 8
1.
12
b101111 0
1$
#206
0$
#208
b110000 0
0.
02
1$
#210
0$
#212
b1000010 #
b1000010 -
b1000010 ,
b1000010 :
b1001 )
b1001 7
b1001 9
b1 6
b1000000 !
b1000000 (
b1000000 8
1.
12
b110001 0
1$
#214
0$
#216
b110010 0
0.
02
1$
#218
0$
#220
b1000110 #
b1000110 -
b1000110 ,
b1000110 :
b1010 )
b1010 7
b1010 9
b10 6
b100000 !
b100000 (
b100000 8
1.
12
b110011 0
1$
#222
0$
#224
b110100 0
0.
02
1$
#226
0$
#228
b1001010 #
b1001010 -
b1001010 ,
b1001010 :
b1011 )
b1011 7
b1011 9
b11 6
b10000 !
b10000 (
b10000 8
1.
12
b110101 0
1$
#230
0$
#232
b110110 0
0.
02
1$
#234
0$
#236
b1010010 #
b1010010 -
b1010010 ,
b1010010 :
b1100 )
b1100 7
b1100 9
b100 6
b1000 !
b1000 (
b1000 8
1.
12
b110111 0
1$
#238
0$
#240
b111000 0
0.
02
1$
#242
0$
#244
b1100010 #
b1100010 -
b1100010 ,
b1100010 :
b1101 )
b1101 7
b1101 9
b101 6
b100 !
b100 (
b100 8
1.
12
b111001 0
1$
#246
0$
#248
b111010 0
0.
02
1$
#250
0$
#252
b111100 #
b111100 -
b111100 ,
b111100 :
b1110 )
b1110 7
b1110 9
b110 6
b10 !
b10 (
b10 8
1.
12
b111011 0
1$
#254
0$
#256
b111100 0
0.
02
1$
#258
0$
#260
b0 #
b0 -
b0 ,
b0 :
b1111 )
b1111 7
b1111 9
b111 6
b1 !
b1 (
b1 8
1.
12
b111101 0
1$
#262
0$
#264
b111110 0
0.
02
1$
#266
0$
#268
b111100 #
b111100 -
b111100 ,
b111100 :
b1000 )
b1000 7
b1000 9
b0 6
b10000000 !
b10000000 (
b10000000 8
1.
12
b111111 0
1$
#270
0$
#272
0/
b0 0
0.
02
1$
#274
0$
#276
b1000010 #
b1000010 -
b1000010 ,
b1000010 :
b1001 )
b1001 7
b1001 9
b1 6
b1000000 !
b1000000 (
b1000000 8
1.
12
b1 0
1$
#278
0$
#280
b10 0
0.
02
1$
#282
0$
#284
b1000110 #
b1000110 -
b1000110 ,
b1000110 :
b1010 )
b1010 7
b1010 9
b10 6
b100000 !
b100000 (
b100000 8
1.
12
b11 0
1$
#286
0$
#288
b100 0
0.
02
1$
#290
0$
#292
b1001010 #
b1001010 -
b1001010 ,
b1001010 :
b1011 )
b1011 7
b1011 9
b11 6
b10000 !
b10000 (
b10000 8
1.
12
b101 0
1$
#294
0$
#296
b110 0
0.
02
1$
#298
0$
#300
b1010010 #
b1010010 -
b1010010 ,
b1010010 :
b1100 )
b1100 7
b1100 9
b100 6
b1000 !
b1000 (
b1000 8
1.
12
b111 0
1$
#302
0$
#304
b1000 0
0.
02
1$
#306
0$
#308
b1100010 #
b1100010 -
b1100010 ,
b1100010 :
b1101 )
b1101 7
b1101 9
b101 6
b100 !
b100 (
b100 8
1.
12
b1001 0
1$
#310
0$
#312
b1010 0
0.
02
1$
#314
0$
#316
b111100 #
b111100 -
b111100 ,
b111100 :
b1110 )
b1110 7
b1110 9
b110 6
b10 !
b10 (
b10 8
1.
12
b1011 0
1$
#318
0$
#320
b1100 0
0.
02
1$
#322
0$
#324
b0 #
b0 -
b0 ,
b0 :
b1111 )
b1111 7
b1111 9
b111 6
b1 !
b1 (
b1 8
1.
12
b1101 0
1$
#326
0$
#328
b1110 0
0.
02
1$
#330
0$
#332
b111100 #
b111100 -
b111100 ,
b111100 :
b1000 )
b1000 7
b1000 9
b0 6
b10000000 !
b10000000 (
b10000000 8
1.
12
b1111 0
1$
#334
0$
#336
b10000 0
0.
02
1$
#338
0$
#340
b1000010 #
b1000010 -
b1000010 ,
b1000010 :
b1001 )
b1001 7
b1001 9
b1 6
b1000000 !
b1000000 (
b1000000 8
1.
12
b10001 0
1$
#342
0$
#344
b10010 0
0.
02
1$
#346
0$
#348
b1000110 #
b1000110 -
b1000110 ,
b1000110 :
b1010 )
b1010 7
b1010 9
b10 6
b100000 !
b100000 (
b100000 8
1.
12
b10011 0
1$
#350
0$
#352
b10100 0
0.
02
1$
#354
0$
#356
b1001010 #
b1001010 -
b1001010 ,
b1001010 :
b1011 )
b1011 7
b1011 9
b11 6
b10000 !
b10000 (
b10000 8
1.
12
b10101 0
1$
#358
0$
#360
b10110 0
0.
02
1$
#362
0$
#364
b1010010 #
b1010010 -
b1010010 ,
b1010010 :
b1100 )
b1100 7
b1100 9
b100 6
b1000 !
b1000 (
b1000 8
1.
12
b10111 0
1$
#366
0$
#368
b11000 0
0.
02
1$
#370
0$
#372
b1100010 #
b1100010 -
b1100010 ,
b1100010 :
b1101 )
b1101 7
b1101 9
b101 6
b100 !
b100 (
b100 8
1.
12
b11001 0
1$
#374
0$
#376
b11010 0
0.
02
1$
#378
0$
#380
b111100 #
b111100 -
b111100 ,
b111100 :
b1110 )
b1110 7
b1110 9
b110 6
b10 !
b10 (
b10 8
1.
12
b11011 0
1$
#382
0$
#384
b11100 0
0.
02
1$
#386
0$
#388
b0 #
b0 -
b0 ,
b0 :
b1111 )
b1111 7
b1111 9
b111 6
b1 !
b1 (
b1 8
1.
12
b11101 0
1$
#390
0$
#392
b11110 0
0.
02
1$
#394
0$
#396
b111100 #
b111100 -
b111100 ,
b111100 :
b1000 )
b1000 7
b1000 9
b0 6
b10000000 !
b10000000 (
b10000000 8
1.
12
b11111 0
1$
#398
0$
#400
b10000 *
b10000 4
b10000 5
1/
b100000 0
0.
02
1$
#402
0$
#404
b11000 #
b11000 -
b11000 ,
b11000 :
b10001 )
b10001 7
b10001 9
b1 6
b1000000 !
b1000000 (
b1000000 8
1.
12
b100001 0
1$
#406
0$
#408
b100010 0
0.
02
1$
#410
0$
#412
b1000 #
b1000 -
b1000 ,
b1000 :
b10010 )
b10010 7
b10010 9
b10 6
b100000 !
b100000 (
b100000 8
1.
12
b100011 0
1$
#414
0$
#416
b100100 0
0.
02
1$
#418
0$
#420
b10011 )
b10011 7
b10011 9
b11 6
b10000 !
b10000 (
b10000 8
1.
12
b100101 0
1$
#422
0$
#424
b100110 0
0.
02
1$
#426
0$
#428
b10100 )
b10100 7
b10100 9
b100 6
b1000 !
b1000 (
b1000 8
1.
12
b100111 0
1$
#430
0$
#432
b101000 0
0.
02
1$
#434
0$
#436
b10101 )
b10101 7
b10101 9
b101 6
b100 !
b100 (
b100 8
1.
12
b101001 0
1$
#438
0$
#440
b101010 0
0.
02
1$
#442
0$
#444
b11100 #
b11100 -
b11100 ,
b11100 :
b10110 )
b10110 7
b10110 9
b110 6
b10 !
b10 (
b10 8
1.
12
b101011 0
1$
#446
0$
#448
b101100 0
0.
02
1$
#450
0$
#452
b0 #
b0 -
b0 ,
b0 :
b10111 )
b10111 7
b10111 9
b111 6
b1 !
b1 (
b1 8
1.
12
b101101 0
1$
#454
0$
#456
b101110 0
0.
02
1$
#458
0$
#460
b1000 #
b1000 -
b1000 ,
b1000 :
b10000 )
b10000 7
b10000 9
b0 6
b10000000 !
b10000000 (
b10000000 8
1.
12
b101111 0
1$
#462
0$
#464
b110000 0
0.
02
1$
#466
0$
#468
b11000 #
b11000 -
b11000 ,
b11000 :
b10001 )
b10001 7
b10001 9
b1 6
b1000000 !
b1000000 (
b1000000 8
1.
12
b110001 0
1$
#470
0$
#472
b110010 0
0.
02
1$
#474
0$
#476
b1000 #
b1000 -
b1000 ,
b1000 :
b10010 )
b10010 7
b10010 9
b10 6
b100000 !
b100000 (
b100000 8
1.
12
b110011 0
1$
#478
0$
#480
b110100 0
0.
02
1$
#482
0$
#484
b10011 )
b10011 7
b10011 9
b11 6
b10000 !
b10000 (
b10000 8
1.
12
b110101 0
1$
#486
0$
#488
b110110 0
0.
02
1$
#490
0$
#492
b10100 )
b10100 7
b10100 9
b100 6
b1000 !
b1000 (
b1000 8
1.
12
b110111 0
1$
#494
0$
#496
b111000 0
0.
02
1$
#498
0$
#500
b10101 )
b10101 7
b10101 9
b101 6
b100 !
b100 (
b100 8
1.
12
b111001 0
1$
#502
0$
#504
b111010 0
0.
02
1$
#506
0$
#508
b11100 #
b11100 -
b11100 ,
b11100 :
b10110 )
b10110 7
b10110 9
b110 6
b10 !
b10 (
b10 8
1.
12
b111011 0
1$
#510
0$
#512
b111100 0
0.
02
1$
#514
0$
#516
b0 #
b0 -
b0 ,
b0 :
b10111 )
b10111 7
b10111 9
b111 6
b1 !
b1 (
b1 8
1.
12
b111101 0
1$
#518
0$
#520
b111110 0
0.
02
1$
#522
0$
#524
b1000 #
b1000 -
b1000 ,
b1000 :
b10000 )
b10000 7
b10000 9
b0 6
b10000000 !
b10000000 (
b10000000 8
1.
12
b111111 0
1$
#526
0$
#528
0/
b0 0
0.
02
1$
#530
0$
#532
b11000 #
b11000 -
b11000 ,
b11000 :
b10001 )
b10001 7
b10001 9
b1 6
b1000000 !
b1000000 (
b1000000 8
1.
12
b1 0
1$
#534
0$
#536
b10 0
0.
02
1$
#538
0$
#540
b1000 #
b1000 -
b1000 ,
b1000 :
b10010 )
b10010 7
b10010 9
b10 6
b100000 !
b100000 (
b100000 8
1.
12
b11 0
1$
#542
0$
#544
b100 0
0.
02
1$
#546
0$
#548
b10011 )
b10011 7
b10011 9
b11 6
b10000 !
b10000 (
b10000 8
1.
12
b101 0
1$
#550
0$
#552
b110 0
0.
02
1$
#554
0$
#556
b10100 )
b10100 7
b10100 9
b100 6
b1000 !
b1000 (
b1000 8
1.
12
b111 0
1$
#558
0$
#560
b1000 0
0.
02
1$
#562
0$
#564
b10101 )
b10101 7
b10101 9
b101 6
b100 !
b100 (
b100 8
1.
12
b1001 0
1$
#566
0$
#568
b1010 0
0.
02
1$
#570
0$
#572
b11100 #
b11100 -
b11100 ,
b11100 :
b10110 )
b10110 7
b10110 9
b110 6
b10 !
b10 (
b10 8
1.
12
b1011 0
1$
#574
0$
#576
b1100 0
0.
02
1$
#578
0$
#580
b0 #
b0 -
b0 ,
b0 :
b10111 )
b10111 7
b10111 9
b111 6
b1 !
b1 (
b1 8
1.
12
b1101 0
1$
#582
0$
#584
b1110 0
0.
02
1$
#586
0$
#588
b1000 #
b1000 -
b1000 ,
b1000 :
b10000 )
b10000 7
b10000 9
b0 6
b10000000 !
b10000000 (
b10000000 8
1.
12
b1111 0
1$
#590
0$
#592
b10000 0
0.
02
1$
#594
0$
#596
b11000 #
b11000 -
b11000 ,
b11000 :
b10001 )
b10001 7
b10001 9
b1 6
b1000000 !
b1000000 (
b1000000 8
1.
12
b10001 0
1$
#598
0$
#600
b10010 0
0.
02
1$
#602
0$
#604
b1000 #
b1000 -
b1000 ,
b1000 :
b10010 )
b10010 7
b10010 9
b10 6
b100000 !
b100000 (
b100000 8
1.
12
b10011 0
1$
#606
0$
#608
b10100 0
0.
02
1$
#610
0$
#612
b10011 )
b10011 7
b10011 9
b11 6
b10000 !
b10000 (
b10000 8
1.
12
b10101 0
1$
#614
0$
#616
b10110 0
0.
02
1$
#618
0$
#620
b10100 )
b10100 7
b10100 9
b100 6
b1000 !
b1000 (
b1000 8
1.
12
b10111 0
1$
#622
0$
#624
b11000 0
0.
02
1$
#626
0$
#628
b10101 )
b10101 7
b10101 9
b101 6
b100 !
b100 (
b100 8
1.
12
b11001 0
1$
#630
0$
#632
b11010 0
0.
02
1$
#634
0$
#636
b11100 #
b11100 -
b11100 ,
b11100 :
b10110 )
b10110 7
b10110 9
b110 6
b10 !
b10 (
b10 8
1.
12
b11011 0
1$
#638
0$
#640
b11100 0
0.
02
1$
#642
0$
#644
b0 #
b0 -
b0 ,
b0 :
b10111 )
b10111 7
b10111 9
b111 6
b1 !
b1 (
b1 8
1.
12
b11101 0
1$
#646
0$
#648
b11110 0
0.
02
1$
#650
0$
#652
b1000 #
b1000 -
b1000 ,
b1000 :
b10000 )
b10000 7
b10000 9
b0 6
b10000000 !
b10000000 (
b10000000 8
1.
12
b11111 0
1$
#654
0$
#656
b11000 *
b11000 4
b11000 5
1/
b100000 0
0.
02
1$
#658
0$
#660
b1000010 #
b1000010 -
b1000010 ,
b1000010 :
b11001 )
b11001 7
b11001 9
b1 6
b1000000 !
b1000000 (
b1000000 8
1.
12
b100001 0
1$
#662
0$
#664
b100010 0
0.
02
1$
#666
0$
#668
b11010 )
b11010 7
b11010 9
b10 6
b100000 !
b100000 (
b100000 8
1.
12
b100011 0
1$
#670
0$
#672
b100100 0
0.
02
1$
#674
0$
#676
b100 #
b100 -
b100 ,
b100 :
b11011 )
b11011 7
b11011 9
b11 6
b10000 !
b10000 (
b10000 8
1.
12
b100101 0
1$
#678
0$
#680
b100110 0
0.
02
1$
#682
0$
#684
b1000 #
b1000 -
b1000 ,
b1000 :
b11100 )
b11100 7
b11100 9
b100 6
b1000 !
b1000 (
b1000 8
1.
12
b100111 0
1$
#686
0$
#688
b101000 0
0.
02
1$
#690
0$
#692
b10000 #
b10000 -
b10000 ,
b10000 :
b11101 )
b11101 7
b11101 9
b101 6
b100 !
b100 (
b100 8
1.
12
b101001 0
1$
#694
0$
#696
b101010 0
0.
02
1$
#698
0$
#700
b1111110 #
b1111110 -
b1111110 ,
b1111110 :
b11110 )
b11110 7
b11110 9
b110 6
b10 !
b10 (
b10 8
1.
12
b101011 0
1$
#702
0$
#704
b101100 0
0.
02
1$
#706
0$
#708
b0 #
b0 -
b0 ,
b0 :
b11111 )
b11111 7
b11111 9
b111 6
b1 !
b1 (
b1 8
1.
12
b101101 0
1$
#710
0$
#712
b101110 0
0.
02
1$
#714
0$
#716
b111100 #
b111100 -
b111100 ,
b111100 :
b11000 )
b11000 7
b11000 9
b0 6
b10000000 !
b10000000 (
b10000000 8
1.
12
b101111 0
1$
#718
0$
#720
b110000 0
0.
02
1$
#722
0$
#724
b1000010 #
b1000010 -
b1000010 ,
b1000010 :
b11001 )
b11001 7
b11001 9
b1 6
b1000000 !
b1000000 (
b1000000 8
1.
12
b110001 0
1$
#726
0$
#728
b110010 0
0.
02
1$
#730
0$
#732
b11010 )
b11010 7
b11010 9
b10 6
b100000 !
b100000 (
b100000 8
1.
12
b110011 0
1$
#734
0$
#736
b110100 0
0.
02
1$
#738
0$
#740
b100 #
b100 -
b100 ,
b100 :
b11011 )
b11011 7
b11011 9
b11 6
b10000 !
b10000 (
b10000 8
1.
12
b110101 0
1$
#742
0$
#744
b110110 0
0.
02
1$
#746
0$
#748
b1000 #
b1000 -
b1000 ,
b1000 :
b11100 )
b11100 7
b11100 9
b100 6
b1000 !
b1000 (
b1000 8
1.
12
b110111 0
1$
#750
0$
#752
b111000 0
0.
02
1$
#754
0$
#756
b10000 #
b10000 -
b10000 ,
b10000 :
b11101 )
b11101 7
b11101 9
b101 6
b100 !
b100 (
b100 8
1.
12
b111001 0
1$
#758
0$
#760
b111010 0
0.
02
1$
#762
0$
#764
b1111110 #
b1111110 -
b1111110 ,
b1111110 :
b11110 )
b11110 7
b11110 9
b110 6
b10 !
b10 (
b10 8
1.
12
b111011 0
1$
#766
0$
#768
b111100 0
0.
02
1$
#770
0$
#772
b0 #
b0 -
b0 ,
b0 :
b11111 )
b11111 7
b11111 9
b111 6
b1 !
b1 (
b1 8
1.
12
b111101 0
1$
#774
0$
#776
b111110 0
0.
02
1$
#778
0$
#780
b111100 #
b111100 -
b111100 ,
b111100 :
b11000 )
b11000 7
b11000 9
b0 6
b10000000 !
b10000000 (
b10000000 8
1.
12
b111111 0
1$
#782
0$
#784
0/
b0 0
0.
02
1$
#786
0$
#788
b1000010 #
b1000010 -
b1000010 ,
b1000010 :
b11001 )
b11001 7
b11001 9
b1 6
b1000000 !
b1000000 (
b1000000 8
1.
12
b1 0
1$
#790
0$
#792
b10 0
0.
02
1$
#794
0$
#796
b11010 )
b11010 7
b11010 9
b10 6
b100000 !
b100000 (
b100000 8
1.
12
b11 0
1$
#798
0$
#800
b100 0
0.
02
1$
#802
0$
#804
b100 #
b100 -
b100 ,
b100 :
b11011 )
b11011 7
b11011 9
b11 6
b10000 !
b10000 (
b10000 8
1.
12
b101 0
1$
#806
0$
#808
b110 0
0.
02
1$
#810
0$
#812
b1000 #
b1000 -
b1000 ,
b1000 :
b11100 )
b11100 7
b11100 9
b100 6
b1000 !
b1000 (
b1000 8
1.
12
b111 0
1$
#814
0$
#816
b1000 0
0.
02
1$
#818
0$
#820
b10000 #
b10000 -
b10000 ,
b10000 :
b11101 )
b11101 7
b11101 9
b101 6
b100 !
b100 (
b100 8
1.
12
b1001 0
1$
#822
0$
#824
b1010 0
0.
02
1$
#826
0$
#828
b1111110 #
b1111110 -
b1111110 ,
b1111110 :
b11110 )
b11110 7
b11110 9
b110 6
b10 !
b10 (
b10 8
1.
12
b1011 0
1$
#830
0$
#832
b1100 0
0.
02
1$
#834
0$
